<?xml version="1.0" encoding="UTF-8"?>
<root>
 <SoundPoints>
  <SoundPoint>
   <Name>XS_OceanLoop</Name>
   <Tag>Ocean</Tag>
   <X>52200.</X>
   <Y>35700.</Y>
   <Z>2487.</Z>
  </SoundPoint>
  <SoundPoint>
   <Name>XS_OceanLoop</Name>
   <Tag>Ocean</Tag>
   <X>49200.</X>
   <Y>29300.</Y>
   <Z>2487.</Z>
  </SoundPoint>
  <SoundPoint>
   <Name>XS_OceanLoop</Name>
   <Tag>Ocean</Tag>
   <X>50300.</X>
   <Y>23100.</Y>
   <Z>2487.</Z>
  </SoundPoint>
  <SoundPoint>
   <Name>XS_OceanLoop</Name>
   <Tag>Ocean</Tag>
   <X>47900.</X>
   <Y>16900.</Y>
   <Z>2487.</Z>
  </SoundPoint>
  <SoundPoint>
   <Name>XS_OceanLoop</Name>
   <Tag>Ocean</Tag>
   <X>44400.</X>
   <Y>11700.</Y>
   <Z>2487.</Z>
  </SoundPoint>
  <SoundPoint>
   <Name>XS_OceanLoop</Name>
   <Tag>Ocean</Tag>
   <X>40300.</X>
   <Y>7600.</Y>
   <Z>2487.</Z>
  </SoundPoint>
  <SoundPoint>
   <Name>XS_OceanLoop</Name>
   <Tag>Ocean</Tag>
   <X>34800.</X>
   <Y>5500.</Y>
   <Z>2399.</Z>
  </SoundPoint>
  <SoundPoint>
   <Name>XS_OceanLoop</Name>
   <Tag>Ocean</Tag>
   <X>31400.</X>
   <Y>7600.</Y>
   <Z>2487.</Z>
  </SoundPoint>
  <SoundPoint>
   <Name>XS_OceanLoop</Name>
   <Tag>Ocean</Tag>
   <X>26200.</X>
   <Y>7700.</Y>
   <Z>2487.</Z>
  </SoundPoint>
  <SoundPoint>
   <Name>XS_OceanLoop</Name>
   <Tag>Ocean</Tag>
   <X>22500.</X>
   <Y>11900.</Y>
   <Z>2487.</Z>
  </SoundPoint>
  <SoundPoint>
   <Name>XS_OceanLoop</Name>
   <Tag>Ocean</Tag>
   <X>16900.</X>
   <Y>15100.</Y>
   <Z>2487.</Z>
  </SoundPoint>
  <SoundPoint>
   <Name>XS_OceanLoop</Name>
   <Tag>Ocean</Tag>
   <X>13600.</X>
   <Y>18900.</Y>
   <Z>2487.</Z>
  </SoundPoint>
  <SoundPoint>
   <Name>XS_OceanLoop</Name>
   <Tag>Ocean</Tag>
   <X>9000.</X>
   <Y>22200.</Y>
   <Z>2487.</Z>
  </SoundPoint>
  <SoundPoint>
   <Name>XS_OceanLoop</Name>
   <Tag>Ocean</Tag>
   <X>6800.</X>
   <Y>27400.</Y>
   <Z>2487.</Z>
  </SoundPoint>
  <SoundPoint>
   <Name>XS_OceanLoop</Name>
   <Tag>Ocean</Tag>
   <X>9100.</X>
   <Y>32400.</Y>
   <Z>2591.</Z>
  </SoundPoint>
  <SoundPoint>
   <Name>XS_LakeLarge</Name>
   <Tag>Freezable</Tag>
   <X>14100.</X>
   <Y>36200.</Y>
   <Z>2603.</Z>
  </SoundPoint>
  <SoundPoint>
   <Name>XS_OceanLoop</Name>
   <Tag>Ocean</Tag>
   <X>10500.</X>
   <Y>39800.</Y>
   <Z>2487.</Z>
  </SoundPoint>
  <SoundPoint>
   <Name>XS_OceanLoop</Name>
   <Tag>Ocean</Tag>
   <X>6900.</X>
   <Y>36100.</Y>
   <Z>2487.</Z>
  </SoundPoint>
  <SoundPoint>
   <Name>XS_OceanLoop</Name>
   <Tag>Ocean</Tag>
   <X>2400.</X>
   <Y>22500.</Y>
   <Z>2487.</Z>
  </SoundPoint>
  <SoundPoint>
   <Name>XS_OceanLoop</Name>
   <Tag>Ocean</Tag>
   <X>2500.</X>
   <Y>27200.</Y>
   <Z>2487.</Z>
  </SoundPoint>
  <SoundPoint>
   <Name>XS_OceanLoop</Name>
   <Tag>Ocean</Tag>
   <X>8700.</X>
   <Y>17600.</Y>
   <Z>2487.</Z>
  </SoundPoint>
  <SoundPoint>
   <Name>XS_OceanLoop</Name>
   <Tag>Ocean</Tag>
   <X>9500.</X>
   <Y>12000.</Y>
   <Z>2487.</Z>
  </SoundPoint>
  <SoundPoint>
   <Name>XS_OceanLoop</Name>
   <Tag>Ocean</Tag>
   <X>17800.</X>
   <Y>8800.</Y>
   <Z>2487.</Z>
  </SoundPoint>
  <SoundPoint>
   <Name>XS_OceanLoop</Name>
   <Tag>Ocean</Tag>
   <X>56000.</X>
   <Y>29400.</Y>
   <Z>2487.</Z>
  </SoundPoint>
  <SoundPoint>
   <Name>XS_Ocean</Name>
   <Tag>Ocean</Tag>
   <X>5200.</X>
   <Y>34700.</Y>
   <Z>2487.</Z>
  </SoundPoint>
  <SoundPoint>
   <Name>XS_Ocean</Name>
   <Tag>Ocean</Tag>
   <X>12000.</X>
   <Y>35700.</Y>
   <Z>3473.</Z>
  </SoundPoint>
  <SoundPoint>
   <Name>XS_Ocean</Name>
   <Tag>Ocean</Tag>
   <X>7000.</X>
   <Y>24300.</Y>
   <Z>2487.</Z>
  </SoundPoint>
  <SoundPoint>
   <Name>XS_Ocean</Name>
   <Tag>Ocean</Tag>
   <X>13300.</X>
   <Y>17700.</Y>
   <Z>2487.</Z>
  </SoundPoint>
  <SoundPoint>
   <Name>XS_Ocean</Name>
   <Tag>Ocean</Tag>
   <X>18000.</X>
   <Y>13500.</Y>
   <Z>2487.</Z>
  </SoundPoint>
  <SoundPoint>
   <Name>XS_Ocean</Name>
   <Tag>Ocean</Tag>
   <X>21900.</X>
   <Y>10000.</Y>
   <Z>2487.</Z>
  </SoundPoint>
  <SoundPoint>
   <Name>XS_Ocean</Name>
   <Tag>Ocean</Tag>
   <X>26300.</X>
   <Y>6500.</Y>
   <Z>2487.</Z>
  </SoundPoint>
  <SoundPoint>
   <Name>XS_Ocean</Name>
   <Tag>Ocean</Tag>
   <X>31200.</X>
   <Y>6000.</Y>
   <Z>2487.</Z>
  </SoundPoint>
  <SoundPoint>
   <Name>XS_Ocean</Name>
   <Tag>Ocean</Tag>
   <X>34600.</X>
   <Y>4400.</Y>
   <Z>2487.</Z>
  </SoundPoint>
  <SoundPoint>
   <Name>XS_Ocean</Name>
   <Tag>Ocean</Tag>
   <X>40400.</X>
   <Y>6400.</Y>
   <Z>2487.</Z>
  </SoundPoint>
  <SoundPoint>
   <Name>XS_Ocean</Name>
   <Tag>Ocean</Tag>
   <X>45400.</X>
   <Y>11500.</Y>
   <Z>2487.</Z>
  </SoundPoint>
  <SoundPoint>
   <Name>XS_Ocean</Name>
   <Tag>Ocean</Tag>
   <X>48800.</X>
   <Y>15900.</Y>
   <Z>2487.</Z>
  </SoundPoint>
  <SoundPoint>
   <Name>XS_Ocean</Name>
   <Tag>Ocean</Tag>
   <X>51200.</X>
   <Y>22700.</Y>
   <Z>2487.</Z>
  </SoundPoint>
  <SoundPoint>
   <Name>XS_Ocean</Name>
   <Tag>Ocean</Tag>
   <X>50200.</X>
   <Y>28300.</Y>
   <Z>2487.</Z>
  </SoundPoint>
  <SoundPoint>
   <Name>XS_Ocean</Name>
   <Tag>Ocean</Tag>
   <X>52600.</X>
   <Y>34800.</Y>
   <Z>2487.</Z>
  </SoundPoint>
  <SoundPoint>
   <Name>XS_LakeLarge</Name>
   <Tag>Freezable</Tag>
   <X>47800.</X>
   <Y>33900.</Y>
   <Z>2487.</Z>
  </SoundPoint>
  <SoundPoint>
   <Name>XS_LakeLarge</Name>
   <Tag>Freezable</Tag>
   <X>36900.</X>
   <Y>10000.</Y>
   <Z>2487.</Z>
  </SoundPoint>
  <SoundPoint>
   <Name>XS_LakeLarge</Name>
   <Tag>Freezable</Tag>
   <X>9600.</X>
   <Y>38100.</Y>
   <Z>2487.</Z>
  </SoundPoint>
  <SoundPoint>
   <Name>XS_RiverMedium</Name>
   <Tag>Freezable</Tag>
   <X>13900.</X>
   <Y>30900.</Y>
   <Z>2487.</Z>
  </SoundPoint>
  <SoundPoint>
   <Name>XS_RiverMedium</Name>
   <Tag>Freezable</Tag>
   <X>14000.</X>
   <Y>23400.</Y>
   <Z>2487.</Z>
  </SoundPoint>
  <SoundPoint>
   <Name>XS_RiverMedium</Name>
   <Tag>Freezable</Tag>
   <X>47100.</X>
   <Y>21200.</Y>
   <Z>2487.</Z>
  </SoundPoint>
  <SoundPoint>
   <Name>XS_RiverSmall</Name>
   <Tag>Freezable</Tag>
   <X>45500.</X>
   <Y>26100.</Y>
   <Z>2487.</Z>
  </SoundPoint>
  <SoundPoint>
   <Name>XS_RiverSmall</Name>
   <Tag>Freezable</Tag>
   <X>43900.</X>
   <Y>30500.</Y>
   <Z>2487.</Z>
  </SoundPoint>
  <SoundPoint>
   <Name>XS_RiverMedium</Name>
   <Tag>Freezable</Tag>
   <X>42300.</X>
   <Y>32400.</Y>
   <Z>2487.</Z>
  </SoundPoint>
  <SoundPoint>
   <Name>XS_RiverMedium</Name>
   <Tag>Freezable</Tag>
   <X>36000.</X>
   <Y>33000.</Y>
   <Z>2487.</Z>
  </SoundPoint>
  <SoundPoint>
   <Name>XS_RiverMedium</Name>
   <Tag>Freezable</Tag>
   <X>31000.</X>
   <Y>34900.</Y>
   <Z>2487.</Z>
  </SoundPoint>
  <SoundPoint>
   <Name>XS_RiverSmall</Name>
   <Tag>Freezable</Tag>
   <X>29000.</X>
   <Y>35100.</Y>
   <Z>2487.</Z>
  </SoundPoint>
  <SoundPoint>
   <Name>XS_RiverSmall</Name>
   <Tag>Freezable</Tag>
   <X>24300.</X>
   <Y>38200.</Y>
   <Z>2487.</Z>
  </SoundPoint>
  <SoundPoint>
   <Name>XS_LakeLarge</Name>
   <Tag>Freezable</Tag>
   <X>16100.</X>
   <Y>38800.</Y>
   <Z>2487.</Z>
  </SoundPoint>
  <SoundPoint>
   <Name>XS_LakeLarge</Name>
   <Tag>Freezable</Tag>
   <X>22600.</X>
   <Y>43000.</Y>
   <Z>2487.</Z>
  </SoundPoint>
  <SoundPoint>
   <Name>XS_LakeMedium</Name>
   <Tag>Freezable</Tag>
   <X>20900.</X>
   <Y>39300.</Y>
   <Z>2487.</Z>
  </SoundPoint>
  <SoundPoint>
   <Name>XS_WaterfallLarge</Name>
   <Tag>Waterfall</Tag>
   <X>15900.</X>
   <Y>43000.</Y>
   <Z>2481.</Z>
  </SoundPoint>
  <SoundPoint>
   <Name>XS_WaterfallMedium</Name>
   <Tag>Waterfall</Tag>
   <X>20900.</X>
   <Y>44700.</Y>
   <Z>2354.</Z>
  </SoundPoint>
  <SoundPoint>
   <Name>XS_WaterfallLarge</Name>
   <Tag>Waterfall</Tag>
   <X>17000.</X>
   <Y>50300.</Y>
   <Z>3509.</Z>
  </SoundPoint>
  <SoundPoint>
   <Name>XS_WaterfallMedium</Name>
   <Tag>Waterfall</Tag>
   <X>13200.</X>
   <Y>48300.</Y>
   <Z>3933.</Z>
  </SoundPoint>
  <SoundPoint>
   <Name>XS_RiverMedium</Name>
   <Tag>Freezable</Tag>
   <X>21300.</X>
   <Y>40100.</Y>
   <Z>2487.</Z>
  </SoundPoint>
  <SoundPoint>
   <Name>XS_WaterfallLarge</Name>
   <Tag>Waterfall</Tag>
   <X>12600.</X>
   <Y>48200.</Y>
   <Z>3846.</Z>
  </SoundPoint>
  <SoundPoint>
   <Name>XS_LakeLarge</Name>
   <Tag>Freezable</Tag>
   <X>14200.</X>
   <Y>44700.</Y>
   <Z>3547.</Z>
  </SoundPoint>
  <SoundPoint>
   <Name>XS_LakeLarge</Name>
   <Tag>Freezable</Tag>
   <X>19200.</X>
   <Y>47300.</Y>
   <Z>3547.</Z>
  </SoundPoint>
  <SoundPoint>
   <Name>XS_ForestME</Name>
   <Tag>Forest</Tag>
   <X>21400.</X>
   <Y>51700.</Y>
   <Z>4748.</Z>
  </SoundPoint>
  <SoundPoint>
   <Name>XS_ForestME</Name>
   <Tag>Forest</Tag>
   <X>27600.</X>
   <Y>51700.</Y>
   <Z>4539.</Z>
  </SoundPoint>
  <SoundPoint>
   <Name>XS_ForestME</Name>
   <Tag>Forest</Tag>
   <X>34200.</X>
   <Y>51700.</Y>
   <Z>3944.</Z>
  </SoundPoint>
  <SoundPoint>
   <Name>XS_ForestME</Name>
   <Tag>Forest</Tag>
   <X>40400.</X>
   <Y>48200.</Y>
   <Z>2682.</Z>
  </SoundPoint>
  <SoundPoint>
   <Name>XS_ForestME</Name>
   <Tag>Forest</Tag>
   <X>48200.</X>
   <Y>43900.</Y>
   <Z>5032.</Z>
  </SoundPoint>
  <SoundPoint>
   <Name>XS_ForestME</Name>
   <Tag>Forest</Tag>
   <X>51300.</X>
   <Y>38800.</Y>
   <Z>3385.</Z>
  </SoundPoint>
  <SoundPoint>
   <Name>XS_ForestME</Name>
   <Tag>Forest</Tag>
   <X>42600.</X>
   <Y>41000.</Y>
   <Z>3434.</Z>
  </SoundPoint>
  <SoundPoint>
   <Name>XS_ForestME</Name>
   <Tag>Forest</Tag>
   <X>34800.</X>
   <Y>35800.</Y>
   <Z>2886.</Z>
  </SoundPoint>
  <SoundPoint>
   <Name>XS_ForestME</Name>
   <Tag>Forest</Tag>
   <X>25600.</X>
   <Y>42300.</Y>
   <Z>2661.</Z>
  </SoundPoint>
  <SoundPoint>
   <Name>XS_ForestME</Name>
   <Tag>Forest</Tag>
   <X>38900.</X>
   <Y>24600.</Y>
   <Z>2663.</Z>
  </SoundPoint>
  <SoundPoint>
   <Name>XS_ForestME</Name>
   <Tag>Forest</Tag>
   <X>31200.</X>
   <Y>22800.</Y>
   <Z>2685.</Z>
  </SoundPoint>
  <SoundPoint>
   <Name>XS_ForestME</Name>
   <Tag>Forest</Tag>
   <X>42100.</X>
   <Y>13200.</Y>
   <Z>2667.</Z>
  </SoundPoint>
  <SoundPoint>
   <Name>XS_ForestME</Name>
   <Tag>Forest</Tag>
   <X>24800.</X>
   <Y>22600.</Y>
   <Z>3513.</Z>
  </SoundPoint>
  <SoundPoint>
   <Name>XS_ForestME</Name>
   <Tag>Forest</Tag>
   <X>24100.</X>
   <Y>17800.</Y>
   <Z>2921.</Z>
  </SoundPoint>
  <SoundPoint>
   <Name>XS_ForestME</Name>
   <Tag>Forest</Tag>
   <X>16800.</X>
   <Y>17500.</Y>
   <Z>2606.</Z>
  </SoundPoint>
  <SoundPoint>
   <Name>XS_ForestME</Name>
   <Tag>Forest</Tag>
   <X>17100.</X>
   <Y>23100.</Y>
   <Z>2616.</Z>
  </SoundPoint>
  <SoundPoint>
   <Name>XS_ForestME</Name>
   <Tag>Forest</Tag>
   <X>15000.</X>
   <Y>34400.</Y>
   <Z>2620.</Z>
  </SoundPoint>
  <SoundPoint>
   <Name>XS_ForestME</Name>
   <Tag>Forest</Tag>
   <X>21800.</X>
   <Y>30900.</Y>
   <Z>2655.</Z>
  </SoundPoint>
  <SoundPoint>
   <Name>XS_ForestME</Name>
   <Tag>Forest</Tag>
   <X>27400.</X>
   <Y>10100.</Y>
   <Z>2733.</Z>
  </SoundPoint>
 </SoundPoints>
</root>
